hockey/__init__.py
hockey/setup.py
hockey/player/__init__ .py
hockey/player/get_player_stats.py
hockey/player/goalie.py
hockey/player/player.py
hockey/player/skater.py
hockey/teamstats/__init__.py
hockey/teamstats/basic.py
hockey/teamstats/toplists.py
HockeyPackage-0.0.1.dist-info/METADATA
HockeyPackage-0.0.1.dist-info/WHEEL
HockeyPackage-0.0.1.dist-info/top_level.txt
HockeyPackage-0.0.1.dist-info/RECORD
