Metadata-Version: 2.1
Name: HockeyPackage
Version: 0.0.1
Summary: A package for hockey stats
Author: Tyler Stevenson, Foster Lockerbie
Project-URL: Homepage, https://github.com/stev7198/Data533_Assignment
Classifier: Programming Language :: Python :: 3
Classifier: License :: OSI Approved :: MIT License
Classifier: Operating System :: OS Independent
Requires-Python: >=3.6
